spa_mean_impute/__init__.py
spa_mean_impute/cli.py
spa_mean_impute/imputer.py
spa_mean_impute/utils.py
spameanimpute-0.1.0.dist-info/licenses/LICENSE.txt
spameanimpute-0.1.0.dist-info/METADATA
spameanimpute-0.1.0.dist-info/WHEEL
spameanimpute-0.1.0.dist-info/entry_points.txt
spameanimpute-0.1.0.dist-info/top_level.txt
spameanimpute-0.1.0.dist-info/RECORD
