Metadata-Version: 2.4
Name: SpaMeanImpute
Version: 0.1.0
Summary: Spatial Transcriptomics Imputation Tool (SpaMean-Impute)
Home-page: https://github.com/FahimHafiz/SpaMean-Impute
Author: Fahim Hafiz
Author-email: fahimhafiz@cse.uiu.ac.bd
Classifier: Programming Language :: Python :: 3
Classifier: License :: OSI Approved :: MIT License
Classifier: Operating System :: OS Independent
Requires-Python: >=3.7
License-File: LICENSE.txt
Requires-Dist: scanpy
Requires-Dist: scipy
Requires-Dist: numpy
Requires-Dist: scikit-learn
Requires-Dist: tqdm
Requires-Dist: pandas
Dynamic: author
Dynamic: author-email
Dynamic: classifier
Dynamic: description
Dynamic: description-content-type
Dynamic: home-page
Dynamic: license-file
Dynamic: requires-dist
Dynamic: requires-python
Dynamic: summary
